mcdl.py
mcdl-0.4.0.dist-info/DESCRIPTION.rst
mcdl-0.4.0.dist-info/METADATA
mcdl-0.4.0.dist-info/RECORD
mcdl-0.4.0.dist-info/WHEEL
mcdl-0.4.0.dist-info/entry_points.txt
mcdl-0.4.0.dist-info/metadata.json
mcdl-0.4.0.dist-info/top_level.txt
