Metadata-Version: 2.0
Name: mcdl
Version: 0.4.0
Summary: A program for downloading pre-built Minecraft server software
Home-page: https://github.com/SaltyHash/mcdl
Author: Austin Bowen
Author-email: austin.bowen.314@gmail.com
License: MIT
Keywords: minecraft server management
Platform: UNKNOWN
Classifier: Development Status :: 4 - Beta
Classifier: Intended Audience :: Developers
Classifier: Intended Audience :: System Administrators
Classifier: Topic :: Software Development
Classifier: Topic :: Utilities
Classifier: License :: OSI Approved :: MIT License
Classifier: Natural Language :: English
Classifier: Programming Language :: Python :: 3
Requires-Dist: packaging
Requires-Dist: progress
Requires-Dist: requests
Requires-Dist: six
Requires-Dist: terminaltables
